faytheclient/__init__.py
faytheclient/client.py
faytheclient/exceptions.py
faytheclient/http.py
faytheclient/utils.py
python_faytheclient-0.0.15.dist-info/AUTHORS
python_faytheclient-0.0.15.dist-info/LICENSE
python_faytheclient-0.0.15.dist-info/METADATA
python_faytheclient-0.0.15.dist-info/WHEEL
python_faytheclient-0.0.15.dist-info/pbr.json
python_faytheclient-0.0.15.dist-info/top_level.txt
python_faytheclient-0.0.15.dist-info/RECORD
